tencent_cloud_hackathon_intelligent_pentest_competition_api_server/__init__.py
tencent_cloud_hackathon_intelligent_pentest_competition_api_server/base.py
tencent_cloud_hackathon_intelligent_pentest_competition_api_server/client_cli.py
tencent_cloud_hackathon_intelligent_pentest_competition_api_server/client_mcp.py
tencent_cloud_hackathon_intelligent_pentest_competition_api_server/client_sdk.py
tencent_cloud_hackathon_intelligent_pentest_competition_api_server-0.1.2.dist-info/METADATA
tencent_cloud_hackathon_intelligent_pentest_competition_api_server-0.1.2.dist-info/WHEEL
tencent_cloud_hackathon_intelligent_pentest_competition_api_server-0.1.2.dist-info/top_level.txt
tencent_cloud_hackathon_intelligent_pentest_competition_api_server-0.1.2.dist-info/RECORD
