Metadata-Version: 2.4
Name: tencent-cloud-hackathon-intelligent-pentest-competition-api-server
Version: 0.1.2
Summary: Add your description here
Requires-Python: >=3.12
Requires-Dist: fastmcp>=2.13.0.2
Requires-Dist: pydantic>=2.12.4
Requires-Dist: requests>=2.32.5
Requires-Dist: requests-ratelimiter>=0.7.0
Requires-Dist: typer>=0.20.0
